{"frames": [

{
	"filename": "adult_elephant/0000",
	"frame": {"x":1,"y":1,"w":226,"h":196},
	"rotated": false,
	"trimmed": true,
	"spriteSourceSize": {"x":179,"y":34,"w":226,"h":196},
	"sourceSize": {"w":427,"h":275}
},
{
	"filename": "adult_elephant/0001",
	"frame": {"x":1,"y":1,"w":226,"h":196},
	"rotated": false,
	"trimmed": true,
	"spriteSourceSize": {"x":179,"y":34,"w":226,"h":196},
	"sourceSize": {"w":427,"h":275}
},
{
	"filename": "adult_elephant/0002",
	"frame": {"x":1,"y":1,"w":226,"h":196},
	"rotated": false,
	"trimmed": true,
	"spriteSourceSize": {"x":179,"y":34,"w":226,"h":196},
	"sourceSize": {"w":427,"h":275}
},
{
	"filename": "adult_elephant/0003",
	"frame": {"x":1,"y":1,"w":226,"h":196},
	"rotated": false,
	"trimmed": true,
	"spriteSourceSize": {"x":179,"y":34,"w":226,"h":196},
	"sourceSize": {"w":427,"h":275}
},
{
	"filename": "adult_elephant/0004",
	"frame": {"x":229,"y":1,"w":226,"h":196},
	"rotated": false,
	"trimmed": true,
	"spriteSourceSize": {"x":179,"y":34,"w":226,"h":196},
	"sourceSize": {"w":427,"h":275}
},
{
	"filename": "adult_elephant/0005",
	"frame": {"x":457,"y":1,"w":227,"h":196},
	"rotated": false,
	"trimmed": true,
	"spriteSourceSize": {"x":178,"y":34,"w":227,"h":196},
	"sourceSize": {"w":427,"h":275}
},
{
	"filename": "adult_elephant/0006",
	"frame": {"x":686,"y":1,"w":227,"h":197},
	"rotated": false,
	"trimmed": true,
	"spriteSourceSize": {"x":178,"y":33,"w":227,"h":197},
	"sourceSize": {"w":427,"h":275}
},
{
	"filename": "adult_elephant/0007",
	"frame": {"x":1376,"y":1,"w":227,"h":198},
	"rotated": false,
	"trimmed": true,
	"spriteSourceSize": {"x":178,"y":32,"w":227,"h":198},
	"sourceSize": {"w":427,"h":275}
},
{
	"filename": "adult_elephant/0008",
	"frame": {"x":1605,"y":1,"w":228,"h":198},
	"rotated": false,
	"trimmed": true,
	"spriteSourceSize": {"x":177,"y":32,"w":228,"h":198},
	"sourceSize": {"w":427,"h":275}
},
{
	"filename": "adult_elephant/0009",
	"frame": {"x":1605,"y":1,"w":228,"h":198},
	"rotated": false,
	"trimmed": true,
	"spriteSourceSize": {"x":177,"y":32,"w":228,"h":198},
	"sourceSize": {"w":427,"h":275}
},
{
	"filename": "adult_elephant/0010",
	"frame": {"x":1605,"y":1,"w":228,"h":198},
	"rotated": false,
	"trimmed": true,
	"spriteSourceSize": {"x":177,"y":32,"w":228,"h":198},
	"sourceSize": {"w":427,"h":275}
},
{
	"filename": "adult_elephant/0011",
	"frame": {"x":1605,"y":1,"w":228,"h":198},
	"rotated": false,
	"trimmed": true,
	"spriteSourceSize": {"x":177,"y":32,"w":228,"h":198},
	"sourceSize": {"w":427,"h":275}
},
{
	"filename": "adult_elephant/0012",
	"frame": {"x":915,"y":1,"w":227,"h":197},
	"rotated": false,
	"trimmed": true,
	"spriteSourceSize": {"x":178,"y":33,"w":227,"h":197},
	"sourceSize": {"w":427,"h":275}
},
{
	"filename": "adult_elephant/0013",
	"frame": {"x":1144,"y":1,"w":230,"h":197},
	"rotated": false,
	"trimmed": true,
	"spriteSourceSize": {"x":175,"y":33,"w":230,"h":197},
	"sourceSize": {"w":427,"h":275}
},
{
	"filename": "adult_elephant/0014",
	"frame": {"x":229,"y":199,"w":237,"h":201},
	"rotated": false,
	"trimmed": true,
	"spriteSourceSize": {"x":168,"y":29,"w":237,"h":201},
	"sourceSize": {"w":427,"h":275}
},
{
	"filename": "adult_elephant/0015",
	"frame": {"x":468,"y":200,"w":243,"h":204},
	"rotated": false,
	"trimmed": true,
	"spriteSourceSize": {"x":162,"y":26,"w":243,"h":204},
	"sourceSize": {"w":427,"h":275}
},
{
	"filename": "adult_elephant/0016",
	"frame": {"x":943,"y":200,"w":235,"h":209},
	"rotated": false,
	"trimmed": true,
	"spriteSourceSize": {"x":170,"y":21,"w":235,"h":209},
	"sourceSize": {"w":427,"h":275}
},
{
	"filename": "adult_elephant/0017",
	"frame": {"x":943,"y":200,"w":235,"h":209},
	"rotated": false,
	"trimmed": true,
	"spriteSourceSize": {"x":170,"y":21,"w":235,"h":209},
	"sourceSize": {"w":427,"h":275}
},
{
	"filename": "adult_elephant/0018",
	"frame": {"x":1689,"y":201,"w":229,"h":214},
	"rotated": false,
	"trimmed": true,
	"spriteSourceSize": {"x":176,"y":16,"w":229,"h":214},
	"sourceSize": {"w":427,"h":275}
},
{
	"filename": "adult_elephant/0019",
	"frame": {"x":1689,"y":201,"w":229,"h":214},
	"rotated": false,
	"trimmed": true,
	"spriteSourceSize": {"x":176,"y":16,"w":229,"h":214},
	"sourceSize": {"w":427,"h":275}
},
{
	"filename": "adult_elephant/0020",
	"frame": {"x":229,"y":402,"w":231,"h":217},
	"rotated": false,
	"trimmed": true,
	"spriteSourceSize": {"x":174,"y":13,"w":231,"h":217},
	"sourceSize": {"w":427,"h":275}
},
{
	"filename": "adult_elephant/0021",
	"frame": {"x":229,"y":402,"w":231,"h":217},
	"rotated": false,
	"trimmed": true,
	"spriteSourceSize": {"x":174,"y":13,"w":231,"h":217},
	"sourceSize": {"w":427,"h":275}
},
{
	"filename": "adult_elephant/0022",
	"frame": {"x":986,"y":412,"w":240,"h":217},
	"rotated": false,
	"trimmed": true,
	"spriteSourceSize": {"x":165,"y":13,"w":240,"h":217},
	"sourceSize": {"w":427,"h":275}
},
{
	"filename": "adult_elephant/0023",
	"frame": {"x":986,"y":412,"w":240,"h":217},
	"rotated": false,
	"trimmed": true,
	"spriteSourceSize": {"x":165,"y":13,"w":240,"h":217},
	"sourceSize": {"w":427,"h":275}
},
{
	"filename": "adult_elephant/0024",
	"frame": {"x":1228,"y":415,"w":246,"h":217},
	"rotated": false,
	"trimmed": true,
	"spriteSourceSize": {"x":159,"y":13,"w":246,"h":217},
	"sourceSize": {"w":427,"h":275}
},
{
	"filename": "adult_elephant/0025",
	"frame": {"x":1228,"y":415,"w":246,"h":217},
	"rotated": false,
	"trimmed": true,
	"spriteSourceSize": {"x":159,"y":13,"w":246,"h":217},
	"sourceSize": {"w":427,"h":275}
},
{
	"filename": "adult_elephant/0026",
	"frame": {"x":1476,"y":417,"w":259,"h":217},
	"rotated": false,
	"trimmed": true,
	"spriteSourceSize": {"x":146,"y":13,"w":259,"h":217},
	"sourceSize": {"w":427,"h":275}
},
{
	"filename": "adult_elephant/0027",
	"frame": {"x":1476,"y":417,"w":259,"h":217},
	"rotated": false,
	"trimmed": true,
	"spriteSourceSize": {"x":146,"y":13,"w":259,"h":217},
	"sourceSize": {"w":427,"h":275}
},
{
	"filename": "adult_elephant/0028",
	"frame": {"x":1,"y":621,"w":268,"h":217},
	"rotated": false,
	"trimmed": true,
	"spriteSourceSize": {"x":137,"y":13,"w":268,"h":217},
	"sourceSize": {"w":427,"h":275}
},
{
	"filename": "adult_elephant/0029",
	"frame": {"x":1,"y":621,"w":268,"h":217},
	"rotated": false,
	"trimmed": true,
	"spriteSourceSize": {"x":137,"y":13,"w":268,"h":217},
	"sourceSize": {"w":427,"h":275}
},
{
	"filename": "adult_elephant/0030",
	"frame": {"x":271,"y":624,"w":261,"h":217},
	"rotated": false,
	"trimmed": true,
	"spriteSourceSize": {"x":144,"y":13,"w":261,"h":217},
	"sourceSize": {"w":427,"h":275}
},
{
	"filename": "adult_elephant/0031",
	"frame": {"x":271,"y":624,"w":261,"h":217},
	"rotated": false,
	"trimmed": true,
	"spriteSourceSize": {"x":144,"y":13,"w":261,"h":217},
	"sourceSize": {"w":427,"h":275}
},
{
	"filename": "adult_elephant/0032",
	"frame": {"x":534,"y":629,"w":234,"h":217},
	"rotated": false,
	"trimmed": true,
	"spriteSourceSize": {"x":171,"y":13,"w":234,"h":217},
	"sourceSize": {"w":427,"h":275}
},
{
	"filename": "adult_elephant/0033",
	"frame": {"x":534,"y":629,"w":234,"h":217},
	"rotated": false,
	"trimmed": true,
	"spriteSourceSize": {"x":171,"y":13,"w":234,"h":217},
	"sourceSize": {"w":427,"h":275}
},
{
	"filename": "adult_elephant/0034",
	"frame": {"x":1,"y":399,"w":226,"h":217},
	"rotated": false,
	"trimmed": true,
	"spriteSourceSize": {"x":179,"y":13,"w":226,"h":217},
	"sourceSize": {"w":427,"h":275}
},
{
	"filename": "adult_elephant/0035",
	"frame": {"x":1,"y":399,"w":226,"h":217},
	"rotated": false,
	"trimmed": true,
	"spriteSourceSize": {"x":179,"y":13,"w":226,"h":217},
	"sourceSize": {"w":427,"h":275}
},
{
	"filename": "adult_elephant/0036",
	"frame": {"x":1,"y":399,"w":226,"h":217},
	"rotated": false,
	"trimmed": true,
	"spriteSourceSize": {"x":179,"y":13,"w":226,"h":217},
	"sourceSize": {"w":427,"h":275}
},
{
	"filename": "adult_elephant/0037",
	"frame": {"x":1,"y":399,"w":226,"h":217},
	"rotated": false,
	"trimmed": true,
	"spriteSourceSize": {"x":179,"y":13,"w":226,"h":217},
	"sourceSize": {"w":427,"h":275}
},
{
	"filename": "adult_elephant/0038",
	"frame": {"x":1,"y":399,"w":226,"h":217},
	"rotated": false,
	"trimmed": true,
	"spriteSourceSize": {"x":179,"y":13,"w":226,"h":217},
	"sourceSize": {"w":427,"h":275}
},
{
	"filename": "adult_elephant/0039",
	"frame": {"x":1,"y":399,"w":226,"h":217},
	"rotated": false,
	"trimmed": true,
	"spriteSourceSize": {"x":179,"y":13,"w":226,"h":217},
	"sourceSize": {"w":427,"h":275}
},
{
	"filename": "adult_elephant/0040",
	"frame": {"x":1,"y":399,"w":226,"h":217},
	"rotated": false,
	"trimmed": true,
	"spriteSourceSize": {"x":179,"y":13,"w":226,"h":217},
	"sourceSize": {"w":427,"h":275}
},
{
	"filename": "adult_elephant/0041",
	"frame": {"x":1,"y":399,"w":226,"h":217},
	"rotated": false,
	"trimmed": true,
	"spriteSourceSize": {"x":179,"y":13,"w":226,"h":217},
	"sourceSize": {"w":427,"h":275}
},
{
	"filename": "adult_elephant/0042",
	"frame": {"x":770,"y":631,"w":235,"h":217},
	"rotated": false,
	"trimmed": true,
	"spriteSourceSize": {"x":170,"y":13,"w":235,"h":217},
	"sourceSize": {"w":427,"h":275}
},
{
	"filename": "adult_elephant/0043",
	"frame": {"x":770,"y":631,"w":235,"h":217},
	"rotated": false,
	"trimmed": true,
	"spriteSourceSize": {"x":170,"y":13,"w":235,"h":217},
	"sourceSize": {"w":427,"h":275}
},
{
	"filename": "adult_elephant/0044",
	"frame": {"x":1007,"y":634,"w":262,"h":217},
	"rotated": false,
	"trimmed": true,
	"spriteSourceSize": {"x":143,"y":13,"w":262,"h":217},
	"sourceSize": {"w":427,"h":275}
},
{
	"filename": "adult_elephant/0045",
	"frame": {"x":1007,"y":634,"w":262,"h":217},
	"rotated": false,
	"trimmed": true,
	"spriteSourceSize": {"x":143,"y":13,"w":262,"h":217},
	"sourceSize": {"w":427,"h":275}
},
{
	"filename": "adult_elephant/0046",
	"frame": {"x":1271,"y":636,"w":269,"h":217},
	"rotated": false,
	"trimmed": true,
	"spriteSourceSize": {"x":136,"y":13,"w":269,"h":217},
	"sourceSize": {"w":427,"h":275}
},
{
	"filename": "adult_elephant/0047",
	"frame": {"x":1271,"y":636,"w":269,"h":217},
	"rotated": false,
	"trimmed": true,
	"spriteSourceSize": {"x":136,"y":13,"w":269,"h":217},
	"sourceSize": {"w":427,"h":275}
},
{
	"filename": "adult_elephant/0048",
	"frame": {"x":1542,"y":636,"w":266,"h":217},
	"rotated": false,
	"trimmed": true,
	"spriteSourceSize": {"x":139,"y":13,"w":266,"h":217},
	"sourceSize": {"w":427,"h":275}
},
{
	"filename": "adult_elephant/0049",
	"frame": {"x":1542,"y":636,"w":266,"h":217},
	"rotated": false,
	"trimmed": true,
	"spriteSourceSize": {"x":139,"y":13,"w":266,"h":217},
	"sourceSize": {"w":427,"h":275}
},
{
	"filename": "adult_elephant/0050",
	"frame": {"x":1,"y":840,"w":265,"h":217},
	"rotated": false,
	"trimmed": true,
	"spriteSourceSize": {"x":140,"y":13,"w":265,"h":217},
	"sourceSize": {"w":427,"h":275}
},
{
	"filename": "adult_elephant/0051",
	"frame": {"x":1,"y":840,"w":265,"h":217},
	"rotated": false,
	"trimmed": true,
	"spriteSourceSize": {"x":140,"y":13,"w":265,"h":217},
	"sourceSize": {"w":427,"h":275}
},
{
	"filename": "adult_elephant/0052",
	"frame": {"x":534,"y":850,"w":266,"h":217},
	"rotated": false,
	"trimmed": true,
	"spriteSourceSize": {"x":139,"y":13,"w":266,"h":217},
	"sourceSize": {"w":427,"h":275}
},
{
	"filename": "adult_elephant/0053",
	"frame": {"x":802,"y":853,"w":267,"h":217},
	"rotated": false,
	"trimmed": true,
	"spriteSourceSize": {"x":138,"y":13,"w":267,"h":217},
	"sourceSize": {"w":427,"h":275}
},
{
	"filename": "adult_elephant/0054",
	"frame": {"x":1071,"y":855,"w":267,"h":217},
	"rotated": false,
	"trimmed": true,
	"spriteSourceSize": {"x":138,"y":13,"w":267,"h":217},
	"sourceSize": {"w":427,"h":275}
},
{
	"filename": "adult_elephant/0055",
	"frame": {"x":1340,"y":855,"w":268,"h":217},
	"rotated": false,
	"trimmed": true,
	"spriteSourceSize": {"x":137,"y":13,"w":268,"h":217},
	"sourceSize": {"w":427,"h":275}
},
{
	"filename": "adult_elephant/0056",
	"frame": {"x":1610,"y":855,"w":269,"h":217},
	"rotated": false,
	"trimmed": true,
	"spriteSourceSize": {"x":136,"y":13,"w":269,"h":217},
	"sourceSize": {"w":427,"h":275}
},
{
	"filename": "adult_elephant/0057",
	"frame": {"x":534,"y":1072,"w":270,"h":217},
	"rotated": false,
	"trimmed": true,
	"spriteSourceSize": {"x":135,"y":13,"w":270,"h":217},
	"sourceSize": {"w":427,"h":275}
},
{
	"filename": "adult_elephant/0058",
	"frame": {"x":806,"y":1074,"w":269,"h":217},
	"rotated": false,
	"trimmed": true,
	"spriteSourceSize": {"x":136,"y":13,"w":269,"h":217},
	"sourceSize": {"w":427,"h":275}
},
{
	"filename": "adult_elephant/0059",
	"frame": {"x":1077,"y":1074,"w":272,"h":217},
	"rotated": false,
	"trimmed": true,
	"spriteSourceSize": {"x":133,"y":13,"w":272,"h":217},
	"sourceSize": {"w":427,"h":275}
},
{
	"filename": "adult_elephant/0060",
	"frame": {"x":1351,"y":1074,"w":269,"h":217},
	"rotated": false,
	"trimmed": true,
	"spriteSourceSize": {"x":136,"y":13,"w":269,"h":217},
	"sourceSize": {"w":427,"h":275}
},
{
	"filename": "adult_elephant/0061",
	"frame": {"x":1622,"y":1074,"w":271,"h":217},
	"rotated": false,
	"trimmed": true,
	"spriteSourceSize": {"x":134,"y":13,"w":271,"h":217},
	"sourceSize": {"w":427,"h":275}
},
{
	"filename": "adult_elephant/0062",
	"frame": {"x":1,"y":1281,"w":270,"h":217},
	"rotated": false,
	"trimmed": true,
	"spriteSourceSize": {"x":135,"y":13,"w":270,"h":217},
	"sourceSize": {"w":427,"h":275}
},
{
	"filename": "adult_elephant/0063",
	"frame": {"x":273,"y":1291,"w":273,"h":217},
	"rotated": false,
	"trimmed": true,
	"spriteSourceSize": {"x":132,"y":13,"w":273,"h":217},
	"sourceSize": {"w":427,"h":275}
},
{
	"filename": "adult_elephant/0064",
	"frame": {"x":548,"y":1293,"w":271,"h":217},
	"rotated": false,
	"trimmed": true,
	"spriteSourceSize": {"x":134,"y":13,"w":271,"h":217},
	"sourceSize": {"w":427,"h":275}
},
{
	"filename": "adult_elephant/0065",
	"frame": {"x":821,"y":1293,"w":273,"h":217},
	"rotated": false,
	"trimmed": true,
	"spriteSourceSize": {"x":132,"y":13,"w":273,"h":217},
	"sourceSize": {"w":427,"h":275}
},
{
	"filename": "adult_elephant/0066",
	"frame": {"x":1096,"y":1293,"w":271,"h":217},
	"rotated": false,
	"trimmed": true,
	"spriteSourceSize": {"x":134,"y":13,"w":271,"h":217},
	"sourceSize": {"w":427,"h":275}
},
{
	"filename": "adult_elephant/0067",
	"frame": {"x":1369,"y":1293,"w":270,"h":217},
	"rotated": false,
	"trimmed": true,
	"spriteSourceSize": {"x":135,"y":13,"w":270,"h":217},
	"sourceSize": {"w":427,"h":275}
},
{
	"filename": "adult_elephant/0068",
	"frame": {"x":1641,"y":1293,"w":268,"h":217},
	"rotated": false,
	"trimmed": true,
	"spriteSourceSize": {"x":137,"y":13,"w":268,"h":217},
	"sourceSize": {"w":427,"h":275}
},
{
	"filename": "adult_elephant/0069",
	"frame": {"x":266,"y":1062,"w":266,"h":217},
	"rotated": false,
	"trimmed": true,
	"spriteSourceSize": {"x":139,"y":13,"w":266,"h":217},
	"sourceSize": {"w":427,"h":275}
},
{
	"filename": "adult_elephant/0070",
	"frame": {"x":268,"y":843,"w":264,"h":217},
	"rotated": false,
	"trimmed": true,
	"spriteSourceSize": {"x":141,"y":13,"w":264,"h":217},
	"sourceSize": {"w":427,"h":275}
},
{
	"filename": "adult_elephant/0071",
	"frame": {"x":1,"y":1059,"w":263,"h":217},
	"rotated": false,
	"trimmed": true,
	"spriteSourceSize": {"x":142,"y":13,"w":263,"h":217},
	"sourceSize": {"w":427,"h":275}
},
{
	"filename": "adult_elephant/0072",
	"frame": {"x":1,"y":1059,"w":263,"h":217},
	"rotated": false,
	"trimmed": true,
	"spriteSourceSize": {"x":142,"y":13,"w":263,"h":217},
	"sourceSize": {"w":427,"h":275}
},
{
	"filename": "adult_elephant/0073",
	"frame": {"x":1,"y":1059,"w":263,"h":217},
	"rotated": false,
	"trimmed": true,
	"spriteSourceSize": {"x":142,"y":13,"w":263,"h":217},
	"sourceSize": {"w":427,"h":275}
},
{
	"filename": "adult_elephant/0074",
	"frame": {"x":1,"y":1059,"w":263,"h":217},
	"rotated": false,
	"trimmed": true,
	"spriteSourceSize": {"x":142,"y":13,"w":263,"h":217},
	"sourceSize": {"w":427,"h":275}
},
{
	"filename": "adult_elephant/0075",
	"frame": {"x":723,"y":411,"w":261,"h":216},
	"rotated": false,
	"trimmed": true,
	"spriteSourceSize": {"x":144,"y":14,"w":261,"h":216},
	"sourceSize": {"w":427,"h":275}
},
{
	"filename": "adult_elephant/0076",
	"frame": {"x":462,"y":407,"w":259,"h":215},
	"rotated": false,
	"trimmed": true,
	"spriteSourceSize": {"x":146,"y":15,"w":259,"h":215},
	"sourceSize": {"w":427,"h":275}
},
{
	"filename": "adult_elephant/0077",
	"frame": {"x":1432,"y":201,"w":255,"h":212},
	"rotated": false,
	"trimmed": true,
	"spriteSourceSize": {"x":150,"y":18,"w":255,"h":212},
	"sourceSize": {"w":427,"h":275}
},
{
	"filename": "adult_elephant/0078",
	"frame": {"x":1180,"y":201,"w":250,"h":209},
	"rotated": false,
	"trimmed": true,
	"spriteSourceSize": {"x":155,"y":21,"w":250,"h":209},
	"sourceSize": {"w":427,"h":275}
},
{
	"filename": "adult_elephant/0079",
	"frame": {"x":713,"y":200,"w":228,"h":205},
	"rotated": false,
	"trimmed": true,
	"spriteSourceSize": {"x":177,"y":25,"w":228,"h":205},
	"sourceSize": {"w":427,"h":275}
},
{
	"filename": "adult_elephant/0080",
	"frame": {"x":713,"y":200,"w":228,"h":205},
	"rotated": false,
	"trimmed": true,
	"spriteSourceSize": {"x":177,"y":25,"w":228,"h":205},
	"sourceSize": {"w":427,"h":275}
},
{
	"filename": "adult_elephant/0081",
	"frame": {"x":1,"y":199,"w":226,"h":198},
	"rotated": false,
	"trimmed": true,
	"spriteSourceSize": {"x":179,"y":32,"w":226,"h":198},
	"sourceSize": {"w":427,"h":275}
},
{
	"filename": "adult_elephant/0082",
	"frame": {"x":1,"y":199,"w":226,"h":198},
	"rotated": false,
	"trimmed": true,
	"spriteSourceSize": {"x":179,"y":32,"w":226,"h":198},
	"sourceSize": {"w":427,"h":275}
},
{
	"filename": "adult_elephant/0083",
	"frame": {"x":1,"y":1,"w":226,"h":196},
	"rotated": false,
	"trimmed": true,
	"spriteSourceSize": {"x":179,"y":34,"w":226,"h":196},
	"sourceSize": {"w":427,"h":275}
},
{
	"filename": "adult_elephant/0084",
	"frame": {"x":1,"y":1,"w":226,"h":196},
	"rotated": false,
	"trimmed": true,
	"spriteSourceSize": {"x":179,"y":34,"w":226,"h":196},
	"sourceSize": {"w":427,"h":275}
},
{
	"filename": "adult_elephant/0085",
	"frame": {"x":1,"y":1,"w":226,"h":196},
	"rotated": false,
	"trimmed": true,
	"spriteSourceSize": {"x":179,"y":34,"w":226,"h":196},
	"sourceSize": {"w":427,"h":275}
},
{
	"filename": "adult_elephant/0086",
	"frame": {"x":1,"y":1,"w":226,"h":196},
	"rotated": false,
	"trimmed": true,
	"spriteSourceSize": {"x":179,"y":34,"w":226,"h":196},
	"sourceSize": {"w":427,"h":275}
},
{
	"filename": "adult_elephant/0087",
	"frame": {"x":1,"y":1,"w":226,"h":196},
	"rotated": false,
	"trimmed": true,
	"spriteSourceSize": {"x":179,"y":34,"w":226,"h":196},
	"sourceSize": {"w":427,"h":275}
},
{
	"filename": "adult_elephant/0088",
	"frame": {"x":1,"y":1,"w":226,"h":196},
	"rotated": false,
	"trimmed": true,
	"spriteSourceSize": {"x":179,"y":34,"w":226,"h":196},
	"sourceSize": {"w":427,"h":275}
},
{
	"filename": "adult_elephant/0089",
	"frame": {"x":1,"y":1,"w":226,"h":196},
	"rotated": false,
	"trimmed": true,
	"spriteSourceSize": {"x":179,"y":34,"w":226,"h":196},
	"sourceSize": {"w":427,"h":275}
},
{
	"filename": "adult_elephant/0090",
	"frame": {"x":1,"y":1,"w":226,"h":196},
	"rotated": false,
	"trimmed": true,
	"spriteSourceSize": {"x":179,"y":34,"w":226,"h":196},
	"sourceSize": {"w":427,"h":275}
},
{
	"filename": "adult_elephant/0091",
	"frame": {"x":1,"y":1,"w":226,"h":196},
	"rotated": false,
	"trimmed": true,
	"spriteSourceSize": {"x":179,"y":34,"w":226,"h":196},
	"sourceSize": {"w":427,"h":275}
},
{
	"filename": "adult_elephant/0092",
	"frame": {"x":1,"y":1,"w":226,"h":196},
	"rotated": false,
	"trimmed": true,
	"spriteSourceSize": {"x":179,"y":34,"w":226,"h":196},
	"sourceSize": {"w":427,"h":275}
},
{
	"filename": "adult_elephant/0093",
	"frame": {"x":1,"y":1,"w":226,"h":196},
	"rotated": false,
	"trimmed": true,
	"spriteSourceSize": {"x":179,"y":34,"w":226,"h":196},
	"sourceSize": {"w":427,"h":275}
},
{
	"filename": "adult_elephant/0094",
	"frame": {"x":1,"y":1,"w":226,"h":196},
	"rotated": false,
	"trimmed": true,
	"spriteSourceSize": {"x":179,"y":34,"w":226,"h":196},
	"sourceSize": {"w":427,"h":275}
},
{
	"filename": "adult_elephant/0095",
	"frame": {"x":1,"y":1,"w":226,"h":196},
	"rotated": false,
	"trimmed": true,
	"spriteSourceSize": {"x":179,"y":34,"w":226,"h":196},
	"sourceSize": {"w":427,"h":275}
},
{
	"filename": "adult_elephant/0096",
	"frame": {"x":1,"y":1,"w":226,"h":196},
	"rotated": false,
	"trimmed": true,
	"spriteSourceSize": {"x":179,"y":34,"w":226,"h":196},
	"sourceSize": {"w":427,"h":275}
},
{
	"filename": "adult_elephant/0097",
	"frame": {"x":1,"y":1,"w":226,"h":196},
	"rotated": false,
	"trimmed": true,
	"spriteSourceSize": {"x":179,"y":34,"w":226,"h":196},
	"sourceSize": {"w":427,"h":275}
},
{
	"filename": "adult_elephant/0098",
	"frame": {"x":1,"y":1,"w":226,"h":196},
	"rotated": false,
	"trimmed": true,
	"spriteSourceSize": {"x":179,"y":34,"w":226,"h":196},
	"sourceSize": {"w":427,"h":275}
},
{
	"filename": "adult_elephant/0099",
	"frame": {"x":1,"y":1,"w":226,"h":196},
	"rotated": false,
	"trimmed": true,
	"spriteSourceSize": {"x":179,"y":34,"w":226,"h":196},
	"sourceSize": {"w":427,"h":275}
}],
"meta": {
	"app": "http://www.codeandweb.com/texturepacker",
	"version": "1.0",
	"image": "adult_elephant.png",
	"format": "RGBA8888",
	"size": {"w":1919,"h":1511},
	"scale": "0.41667",
	"smartupdate": "$TexturePacker:SmartUpdate:08e14007aa762cb8626f62c4373e7938:357334ad51dc250c4f9d22d03c961478:4a2a14ad5c6ee1d860a644987156b9d3$"
}
}
